abletoolz/__init__.py
abletoolz/__main__.py
abletoolz/ableton_set.py
abletoolz/ableton_track.py
abletoolz/cli.py
abletoolz/color_tools.py
abletoolz/decode_encode.py
abletoolz/misc.py
abletoolz/plugins.py
abletoolz/utils.py
abletoolz/sample_databaser/__init__.py
abletoolz/sample_databaser/create_db.py
abletoolz-1.1.1.dist-info/LICENSE
abletoolz-1.1.1.dist-info/METADATA
abletoolz-1.1.1.dist-info/WHEEL
abletoolz-1.1.1.dist-info/entry_points.txt
abletoolz-1.1.1.dist-info/top_level.txt
abletoolz-1.1.1.dist-info/RECORD
