Metadata-Version: 2.1
Name: abletoolz
Version: 1.1.1
Summary: Tools made for editing, fixing and analyzing Ableton Live sets.
Author: ElixirBeats
License: GNU GENERAL PUBLIC LICENSE
Project-URL: Homepage, https://github.com/elixirbeats/abletoolz
Project-URL: Repository, https://github.com/elixirbeats/abletoolz
Classifier: Programming Language :: Python
Classifier: Programming Language :: Python :: 3
Classifier: Programming Language :: Python :: 3.10
Classifier: Programming Language :: Python :: 3.11
Classifier: Development Status :: 4 - Beta
Classifier: Topic :: Software Development :: Libraries :: Python Modules
Classifier: Topic :: Utilities
Requires-Python: >=3.10
License-File: LICENSE
Requires-Dist: colorama
Requires-Dist: chardet
Requires-Dist: tqdm
Requires-Dist: colormath
Requires-Dist: pydantic
Requires-Dist: win32-setctime ; platform_system == "Windows"
